purl2vcs/__init__.py
purl2vcs/find_source_repo.py
purl2vcs-2.0.0.dist-info/WHEEL
purl2vcs-2.0.0.dist-info/METADATA
purl2vcs-2.0.0.dist-info/CHANGELOG.rst
purl2vcs-2.0.0.dist-info/CODE_OF_CONDUCT.rst
purl2vcs-2.0.0.dist-info/NOTICE
purl2vcs-2.0.0.dist-info/README.rst
purl2vcs-2.0.0.dist-info/apache-2.0.LICENSE
purl2vcs-2.0.0.dist-info/RECORD
